{
  "processors": [
    {
      "rules": [
        {
          "output_state": {
            "Name": "byg:withering_oak_wood",
            "Properties": {
              "axis": "y"
            }
          },
          "input_predicate": {
            "predicate_type": "minecraft:random_block_match",
            "block": "minecraft:stone",
            "probability": 0.33
          },
          "location_predicate": {
            "predicate_type": "minecraft:always_true"
          }
        },
        {
          "output_state": {
            "Name": "quark:vertical_black_stained_planks"
          },
          "input_predicate": {
            "predicate_type": "minecraft:random_block_match",
            "block": "minecraft:stone",
            "probability": 0.5
          },
          "location_predicate": {
            "predicate_type": "minecraft:always_true"
          }
        },
        {
          "output_state": {
            "Name": "byg:black_sand"
          },
          "input_predicate": {
            "predicate_type": "minecraft:random_block_match",
            "block": "minecraft:stone",
            "probability": 1.0
          },
          "location_predicate": {
            "predicate_type": "minecraft:always_true"
          }
        },
        {
          "output_state": {
            "Name": "byg:red_rock"
          },
          "input_predicate": {
            "predicate_type": "minecraft:random_block_match",
            "block": "minecraft:grass_block",
            "probability": 0.5
          },
          "location_predicate": {
            "predicate_type": "minecraft:always_true"
          }
        },
        {
          "output_state": {
            "Name": "byg:stripped_redwood_wood",
            "Properties": {
              "axis": "y"
            }
          },
          "input_predicate": {
            "predicate_type": "minecraft:random_block_match",
            "block": "minecraft:grass_block",
            "probability": 1.0
          },
          "location_predicate": {
            "predicate_type": "minecraft:always_true"
          }
        },
        {
          "output_state": {
            "Name": "minecraft:red_sand"
          },
          "input_predicate": {
            "predicate_type": "minecraft:random_block_match",
            "block": "minecraft:brown_wool",
            "probability": 1.0
          },
          "location_predicate": {
            "predicate_type": "minecraft:always_true"
          }
        },
        {
          "output_state": {
            "Name": "minecraft:smooth_red_sandstone"
          },
          "input_predicate": {
            "predicate_type": "minecraft:random_block_match",
            "block": "minecraft:dirt",
            "probability": 1.0
          },
          "location_predicate": {
            "predicate_type": "minecraft:always_true"
          }
        },
        {
          "output_state": {
            "Name": "byg:flowering_nightshade_leaves",
            "Properties": {
              "distance": "7",
              "persistent": "false"
            }
          },
          "input_predicate": {
            "predicate_type": "minecraft:random_block_match",
            "block": "minecraft:cyan_wool",
            "probability": 0.25
          },
          "location_predicate": {
            "predicate_type": "minecraft:always_true"
          }
        },
        {
          "output_state": {
            "Name": "byg:blooming_witch_hazel_leaves",
            "Properties": {
              "distance": "7",
              "persistent": "false"
            }
          },
          "input_predicate": {
            "predicate_type": "minecraft:random_block_match",
            "block": "minecraft:cyan_wool",
            "probability": 0.33
          },
          "location_predicate": {
            "predicate_type": "minecraft:always_true"
          }
        },
        {
          "output_state": {
            "Name": "byg:withering_oak_leaves",
            "Properties": {
              "distance": "7",
              "persistent": "false"
            }
          },
          "input_predicate": {
            "predicate_type": "minecraft:random_block_match",
            "block": "minecraft:cyan_wool",
            "probability": 0.5
          },
          "location_predicate": {
            "predicate_type": "minecraft:always_true"
          }
        },
        {
          "output_state": {
            "Name": "byg:holly_berry_leaves",
            "Properties": {
              "distance": "7",
              "persistent": "false"
            }
          },
          "input_predicate": {
            "predicate_type": "minecraft:random_block_match",
            "block": "minecraft:cyan_wool",
            "probability": 1.0
          },
          "location_predicate": {
            "predicate_type": "minecraft:always_true"
          }
        },
        {
          "output_state": {
            "Name": "byg:red_rock"
          },
          "input_predicate": {
            "predicate_type": "minecraft:random_block_match",
            "block": "byg:blue_smooth_sandstone",
            "probability": 0.5
          },
          "location_predicate": {
            "predicate_type": "minecraft:always_true"
          }
        },
        {
          "output_state": {
            "Name": "byg:meadow_dirt"
          },
          "input_predicate": {
            "predicate_type": "minecraft:random_block_match",
            "block": "byg:blue_smooth_sandstone",
            "probability": 1.0
          },
          "location_predicate": {
            "predicate_type": "minecraft:always_true"
          }
        },
        {
          "output_state": {
            "Name": "byg:cryptic_bramble"
          },
          "input_predicate": {
            "predicate_type": "minecraft:random_block_match",
            "block": "minecraft:grass",
            "probability": 0.14
          },
          "location_predicate": {
            "predicate_type": "minecraft:always_true"
          }
        },
        {
          "output_state": {
            "Name": "byg:nightshade_sapling",
            "Properties": {
              "stage": "0"
            }
          },
          "input_predicate": {
            "predicate_type": "minecraft:random_block_match",
            "block": "minecraft:grass",
            "probability": 0.17
          },
          "location_predicate": {
            "predicate_type": "minecraft:always_true"
          }
        },
        {
          "output_state": {
            "Name": "byg:embur_sprouts"
          },
          "input_predicate": {
            "predicate_type": "minecraft:random_block_match",
            "block": "minecraft:grass",
            "probability": 0.2
          },
          "location_predicate": {
            "predicate_type": "minecraft:always_true"
          }
        },
        {
          "output_state": {
            "Name": "byg:reed_thatch_carpet",
            "Properties": {
              "axis": "y"
            }
          },
          "input_predicate": {
            "predicate_type": "minecraft:random_block_match",
            "block": "minecraft:grass",
            "probability": 0.25
          },
          "location_predicate": {
            "predicate_type": "minecraft:always_true"
          }
        },
        {
          "output_state": {
            "Name": "quark:spruce_hedge",
            "Properties": {
              "east": "false",
              "extend": "false",
              "north": "false",
              "south": "false",
              "waterlogged": "false",
              "west": "false"
            }
          },
          "input_predicate": {
            "predicate_type": "minecraft:random_block_match",
            "block": "minecraft:grass",
            "probability": 0.33
          },
          "location_predicate": {
            "predicate_type": "minecraft:always_true"
          }
        },
        {
          "output_state": {
            "Name": "byg:death_cap"
          },
          "input_predicate": {
            "predicate_type": "minecraft:random_block_match",
            "block": "minecraft:grass",
            "probability": 0.5
          },
          "location_predicate": {
            "predicate_type": "minecraft:always_true"
          }
        },
        {
          "output_state": {
            "Name": "minecraft:grass"
          },
          "input_predicate": {
            "predicate_type": "minecraft:random_block_match",
            "block": "minecraft:grass",
            "probability": 1.0
          },
          "location_predicate": {
            "predicate_type": "minecraft:always_true"
          }
        },
        {
          "output_state": {
            "Name": "byg:tall_prairie_grass",
            "Properties": {
              "half": "lower"
            }
          },
          "input_predicate": {
            "block_state": {
              "Name": "minecraft:tall_grass",
              "Properties": {
                "half": "lower"
              }
            },
            "predicate_type": "minecraft:blockstate_match"
          },
          "location_predicate": {
            "predicate_type": "minecraft:always_true"
          }
        },
        {
          "output_state": {
            "Name": "byg:tall_prairie_grass",
            "Properties": {
              "half": "upper"
            }
          },
          "input_predicate": {
            "block_state": {
              "Name": "minecraft:tall_grass",
              "Properties": {
                "half": "upper"
              }
            },
            "predicate_type": "minecraft:blockstate_match"
          },
          "location_predicate": {
            "predicate_type": "minecraft:always_true"
          }
        },
        {
          "output_state": {
            "Name": "byg:clover_patch"
          },
          "input_predicate": {
            "predicate_type": "minecraft:random_block_match",
            "block": "byg:leaf_pile",
            "probability": 0.33
          },
          "location_predicate": {
            "predicate_type": "minecraft:always_true"
          }
        },
        {
          "output_state": {
            "Name": "byg:flower_patch"
          },
          "input_predicate": {
            "predicate_type": "minecraft:random_block_match",
            "block": "byg:leaf_pile",
            "probability": 0.5
          },
          "location_predicate": {
            "predicate_type": "minecraft:always_true"
          }
        },
        {
          "output_state": {
            "Name": "byg:leaf_pile"
          },
          "input_predicate": {
            "predicate_type": "minecraft:random_block_match",
            "block": "byg:leaf_pile",
            "probability": 1.0
          },
          "location_predicate": {
            "predicate_type": "minecraft:always_true"
          }
        },
        {
          "output_state": {
            "Name": "byg:redwood_fence",
            "Properties": {
              "east": "false",
              "north": "false",
              "south": "false",
              "waterlogged": "false",
              "west": "false"
            }
          },
          "input_predicate": {
            "predicate_type": "minecraft:random_block_match",
            "block": "byg:maple_fence",
            "probability": 1.0
          },
          "location_predicate": {
            "predicate_type": "minecraft:always_true"
          }
        },
        {
          "output_state": {
            "Name": "minecraft:lantern",
            "Properties": {
              "hanging": "false",
              "waterlogged": "false"
            }
          },
          "input_predicate": {
            "predicate_type": "minecraft:random_block_match",
            "block": "byg:glowstone_lantern",
            "probability": 1.0
          },
          "location_predicate": {
            "predicate_type": "minecraft:always_true"
          }
        },
        {
          "output_state": {
            "Name": "byg:redwood_slab",
            "Properties": {
              "type": "bottom",
              "waterlogged": "false"
            }
          },
          "input_predicate": {
            "predicate_type": "minecraft:random_block_match",
            "block": "minecraft:spruce_slab",
            "probability": 1.0
          },
          "location_predicate": {
            "predicate_type": "minecraft:always_true"
          }
        }
      ],
      "processor_type": "minecraft:rule"
    }
  ]
}