{
  "smite_bolt": {
    "category": "master",
    "sounds": [
      "the_vault:ability/smite_bolt"
    ]
  },
  "taunt_charm": {
    "category": "master",
    "sounds": [
      "the_vault:ability/taunt_charm",
      "the_vault:ability/taunt_charm_1"
    ]
  },
  "totem": {
    "category": "master",
    "sounds": [
      "the_vault:ability/totem"
    ]
  },
  "smite": {
    "category": "master",
    "sounds": [
      "the_vault:ability/smite"
    ]
  },
  "heal": {
    "category": "master",
    "sounds": [
      "the_vault:ability/heal"
    ]
  },
  "taunt": {
    "category": "master",
    "sounds": [
      "the_vault:ability/taunt"
    ]
  },
  "taunt_repel": {
    "category": "master",
    "sounds": [
      "the_vault:ability/taunt_repel"
    ]
  },
  "mana_shield": {
    "category": "master",
    "sounds": [
      "the_vault:ability/mana_shield"
    ]
  },
  "mana_shield_hit": {
    "category": "master",
    "sounds": [
      "the_vault:ability/mana_shield_hit"
    ]
  },
  "nova_speed": {
    "category": "master",
    "sounds": [
      "the_vault:ability/nova_speed"
    ]
  },
  "dash": {
    "category": "master",
    "sounds": [
      "the_vault:ability/dash"
    ]
  },
  "mega_jump": {
    "category": "master",
    "sounds": [
      "the_vault:ability/mega_jump"
    ]
  },
  "magnet_table": {
    "category": "blocks",
    "sounds": [
      "the_vault:magnet_table"
    ]
  },
  "cleanse": {
    "category": "master",
    "sounds": [
      "the_vault:ability/cleanse"
    ]
  },
  "ghost_walk": {
    "category": "master",
    "sounds": [
      "the_vault:ability/ghost_walk"
    ]
  },
  "invisibility": {
    "category": "master",
    "sounds": [
      "the_vault:ability/invisibility"
    ]
  },
  "night_vision": {
    "category": "master",
    "sounds": [
      "the_vault:ability/night_vision"
    ]
  },
  "rampage": {
    "category": "master",
    "sounds": [
      "the_vault:ability/rampage"
    ]
  },
  "execution": {
    "category": "master",
    "sounds": [
      "the_vault:ability/execution"
    ]
  },
  "empower": {
    "category": "master",
    "sounds": [
      "the_vault:ability/empower"
    ]
  },
  "empower_ice_armour": {
    "category": "master",
    "sounds": [
      "the_vault:ability/empower_ice_armour"
    ]
  },
  "shell": {
    "category": "master",
    "sounds": [
      "the_vault:ability/shell"
    ]
  },
  "shell_porcupine": {
    "category": "master",
    "sounds": [
      "the_vault:ability/shell_porcupine"
    ]
  },
  "shell_quill": {
    "category": "master",
    "sounds": [
      "the_vault:ability/shell_quill"
    ]
  },
  "hunter": {
    "category": "player",
    "sounds": [
      "the_vault:ability/hunter"
    ]
  },
  "robot_hurt": {
    "category": "hostile",
    "sounds": [
      "the_vault:robot/hurt_1",
      "the_vault:robot/hurt_2",
      "the_vault:robot/hurt_3",
      "the_vault:robot/hurt_4"
    ]
  },
  "robot_death": {
    "category": "hostile",
    "sounds": [
      "the_vault:robot/death"
    ]
  },
  "boogie_ambient": {
    "category": "hostile",
    "sounds": [
      "the_vault:boogie/ambient_1",
      "the_vault:boogie/ambient_2"
    ]
  },
  "coin_pile_break": {
    "category": "block",
    "sounds": [
      "the_vault:coin_pile/coin4",
      "the_vault:coin_pile/coin5",
      "the_vault:coin_pile/coin6"
    ]
  },
  "coin_pile_place": {
    "category": "block",
    "sounds": [
      "the_vault:coin_pile/coin1",
      "the_vault:coin_pile/coin2"
    ]
  },
  "coin_single_place": {
    "category": "block",
    "sounds": [
      "the_vault:coin_pile/coin_single1",
      "the_vault:coin_pile/coin_single2",
      "the_vault:coin_pile/coin_single3"
    ]
  },
  "boogie_hurt": {
    "category": "hostile",
    "sounds": [
      "the_vault:boogie/hurt_1",
      "the_vault:boogie/hurt_2",
      "the_vault:boogie/hurt_3"
    ]
  },
  "boogie_death": {
    "category": "hostile",
    "sounds": [
      "the_vault:boogie/death"
    ]
  },
  "goblin_bail": {
    "category": "neutral",
    "sounds": [
      "the_vault:treasure_goblin/bail_1",
      "the_vault:treasure_goblin/bail_2"
    ]
  },
  "goblin_death": {
    "category": "neutral",
    "sounds": [
      "the_vault:treasure_goblin/death"
    ]
  },
  "goblin_hurt": {
    "category": "neutral",
    "sounds": [
      "the_vault:treasure_goblin/hurt_1",
      "the_vault:treasure_goblin/hurt_2",
      "the_vault:treasure_goblin/hurt_3"
    ]
  },
  "goblin_idle": {
    "category": "neutral",
    "sounds": [
      "the_vault:treasure_goblin/idle_1",
      "the_vault:treasure_goblin/idle_2",
      "the_vault:treasure_goblin/idle_3"
    ]
  },
  "vault_dood.idle": {
    "category": "hostile",
    "sounds": [
      {
        "name": "the_vault:vault_dood/idle1",
        "pitch": 1.0
      },
      {
        "name": "the_vault:vault_dood/idle1",
        "pitch": 1.1
      },
      {
        "name": "the_vault:vault_dood/idle1",
        "pitch": 0.9
      },
      {
        "name": "the_vault:vault_dood/idle2",
        "pitch": 1.0
      },
      {
        "name": "the_vault:vault_dood/idle2",
        "pitch": 1.1
      },
      {
        "name": "the_vault:vault_dood/idle2",
        "pitch": 0.9
      }
    ]
  },
  "skeleton_pirate.idle": {
    "category": "hostile",
    "sounds": [
      "the_vault:skeleton_pirate/idle1",
      "the_vault:skeleton_pirate/idle2",
      "the_vault:skeleton_pirate/idle3"
    ]
  },
  "winterwalker.idle": {
    "category": "hostile",
    "sounds": [
      "the_vault:winterwalker/idle1",
      "the_vault:winterwalker/idle2"
    ]
  },
  "winterwalker.step": {
    "category": "hostile",
    "sounds": [
      "the_vault:winterwalker/walk1",
      "the_vault:winterwalker/walk2",
      "the_vault:winterwalker/walk3"
    ]
  },
  "winterwalker.hurt": {
    "category": "hostile",
    "sounds": [
      {
        "name": "the_vault:winterwalker/hurt",
        "pitch": 1.0
      },
      {
        "name": "the_vault:winterwalker/hurt",
        "pitch": 1.1
      },
      {
        "name": "the_vault:winterwalker/hurt",
        "pitch": 0.9
      }
    ]
  },
  "winterwalker.death": {
    "category": "hostile",
    "sounds": [
      {
        "name": "the_vault:winterwalker/death",
        "pitch": 1.0
      },
      {
        "name": "the_vault:winterwalker/death",
        "pitch": 1.1
      },
      {
        "name": "the_vault:winterwalker/death",
        "pitch": 0.9
      }
    ]
  },
  "overgrown_zombie.idle": {
    "category": "hostile",
    "sounds": [
      {
        "name": "the_vault:overgrown_zombie/idle1",
        "pitch": 1.0
      },
      {
        "name": "the_vault:overgrown_zombie/idle1",
        "pitch": 1.1
      },
      {
        "name": "the_vault:overgrown_zombie/idle1",
        "pitch": 0.9
      },
      {
        "name": "the_vault:overgrown_zombie/idle2",
        "pitch": 1.0
      },
      {
        "name": "the_vault:overgrown_zombie/idle2",
        "pitch": 1.1
      },
      {
        "name": "the_vault:overgrown_zombie/idle2",
        "pitch": 0.9
      }
    ]
  },
  "overgrown_zombie.step": {
    "category": "hostile",
    "sounds": [
      "the_vault:overgrown_zombie/step1",
      "the_vault:overgrown_zombie/step2"
    ]
  },
  "overgrown_zombie.hurt": {
    "category": "hostile",
    "sounds": [
      {
        "name": "the_vault:overgrown_zombie/hurt1",
        "pitch": 1.0
      },
      {
        "name": "the_vault:overgrown_zombie/hurt1",
        "pitch": 1.1
      },
      {
        "name": "the_vault:overgrown_zombie/hurt1",
        "pitch": 0.9
      }
    ]
  },
  "overgrown_zombie.death": {
    "category": "hostile",
    "sounds": [
      {
        "name": "the_vault:overgrown_zombie/death",
        "pitch": 1.0
      },
      {
        "name": "the_vault:overgrown_zombie/death",
        "pitch": 1.1
      },
      {
        "name": "the_vault:overgrown_zombie/death",
        "pitch": 0.9
      }
    ]
  },
  "shiver.idle": {
    "category": "hostile",
    "sounds": [
      "the_vault:shiver/idle1",
      "the_vault:shiver/idle2",
      "the_vault:shiver/idle3"
    ]
  },
  "shiver.hurt": {
    "category": "hostile",
    "sounds": [
      "the_vault:shiver/hurt1",
      "the_vault:shiver/hurt2"
    ]
  },
  "shiver.death": {
    "category": "hostile",
    "sounds": [
      {
        "name": "the_vault:shiver/death",
        "pitch": 1.0
      },
      {
        "name": "the_vault:shiver/death",
        "pitch": 1.1
      },
      {
        "name": "the_vault:shiver/death",
        "pitch": 0.9
      }
    ]
  },
  "burp": {
    "sounds": [
      "the_vault:burp/burp1",
      "the_vault:burp/burp2",
      "the_vault:burp/burp3"
    ]
  },
  "witchskall_idle": {
    "category": "neutral",
    "sounds": [
      {
        "name": "the_vault:witchskall/idle",
        "pitch": 1.00
      },
      {
        "name": "the_vault:witchskall/idle",
        "pitch": 0.95
      },
      {
        "name": "the_vault:witchskall/idle",
        "pitch": 1.05
      }
    ]
  },
  "puzzle_completion_major": {
    "category": "master",
    "sounds": [
      "the_vault:puzzle/completion_major"
    ]
  },
  "puzzle_completion_minor": {
    "category": "master",
    "sounds": [
      "the_vault:puzzle/completion_minor"
    ]
  },
  "puzzle_completion_fail": {
    "category": "master",
    "sounds": [
      "the_vault:puzzle/completion_fail"
    ]
  },
  "grasshopper_brrr": {
    "category": "master",
    "sounds": [
      "the_vault:grasshopper_brrr"
    ]
  },
  "raffle": {
    "category": "master",
    "sounds": [
      {
        "name": "the_vault:raffle",
        "volume": 0.9
      }
    ]
  },
  "timer_kill": {
    "category": "master",
    "sounds": [
      "the_vault:timer_kill"
    ]
  },
  "arena_horns": {
    "category": "master",
    "sounds": [
      "the_vault:arena/horns"
    ]
  },
  "vault_ambient_loop": {
    "category": "music",
    "sounds": [
      {
        "name": "the_vault:vault/ambient_loop",
        "stream": true
      }
    ]
  },
  "boss_loop": {
    "category": "music",
    "sounds": [
      {
        "name": "the_vault:vault/boss_loop",
        "stream": true
      }
    ]
  },
  "vault_ambient": {
    "category": "ambient",
    "sounds": [
      "the_vault:vault/ambient_1",
      "the_vault:vault/ambient_2",
      "the_vault:vault/ambient_3",
      "the_vault:vault/ambient_4",
      "the_vault:vault/ambient_5",
      "the_vault:vault/ambient_6",
      "the_vault:vault/ambient_7",
      "the_vault:vault/ambient_8",
      "the_vault:vault/ambient_9",
      "the_vault:vault/ambient_10"
    ]
  },
  "timer_panic_tick": {
    "category": "master",
    "sounds": [
      "the_vault:timer_panic_tick"
    ]
  },
  "confetti": {
    "category": "master",
    "sounds": [
      "the_vault:confetti"
    ]
  },
  "identification": {
    "category": "master",
    "sounds": [
      "the_vault:identification"
    ]
  },
  "gift_bomb": {
    "category": "master",
    "sounds": [
      "the_vault:gift_bomb"
    ]
  },
  "vault_exp": {
    "category": "master",
    "sounds": [
      "the_vault:vault_exp"
    ]
  },
  "vault_level_up": {
    "category": "master",
    "sounds": [
      {
        "name": "the_vault:vault_level_up",
        "volume": 0.8
      }
    ]
  },
  "skill_tree_learn": {
    "category": "master",
    "sounds": [
      "the_vault:skill_tree_learn"
    ]
  },
  "skill_tree_upgrade": {
    "category": "master",
    "sounds": [
      "the_vault:skill_tree_upgrade"
    ]
  },
  "vending_machine": {
    "category": "master",
    "sounds": [
      "the_vault:vending_machine"
    ]
  },
  "boss_tp": {
    "category": "master",
    "sounds": [
      "the_vault:boss_tp"
    ]
  },
  "booster_pack": {
    "category": "master",
    "sounds": [
      {
        "name": "the_vault:booster_pack",
        "volume": 0.5
      }
    ]
  },
  "booster_pack_fail": {
    "category": "master",
    "sounds": [
      {
        "name": "the_vault:booster_pack_fail",
        "volume": 0.5
      }
    ]
  },
  "sub_bomb_gain": {
    "category": "master",
    "sounds": [
      "the_vault:sub_bomb_gain"
    ]
  },
  "sub_bomb_gain_mega": {
    "category": "master",
    "sounds": [
      "the_vault:sub_bomb_gain_mega"
    ]
  },
  "vault_portal_open": {
    "category": "master",
    "sounds": [
      {
        "name": "the_vault:vault_portal_open",
        "volume": 0.5
      }
    ]
  },
  "vault_portal_leave": {
    "category": "master",
    "sounds": [
      "the_vault:vault_portal_leave"
    ]
  },
  "vault_gem_hit": {
    "category": "block",
    "sounds": [
      "the_vault:vault_gem/hit_1",
      "the_vault:vault_gem/hit_2",
      "the_vault:vault_gem/hit_3",
      "the_vault:vault_gem/hit_4",
      "the_vault:vault_gem/hit_5"
    ]
  },
  "vault_gem_break": {
    "category": "block",
    "sounds": [
      "the_vault:vault_gem/break"
    ]
  },
  "vampire_hissing": {
    "category": "master",
    "sounds": [
      "the_vault:vampire_hissing"
    ]
  },
  "cauldron_bubbles": {
    "category": "master",
    "sounds": [
      "the_vault:cauldron_bubbles"
    ]
  },
  "no_sound": {
    "category": "master",
    "sounds": []
  },
  "vault_chest_epic_open": {
    "category": "master",
    "sounds": [
      "the_vault:chest/vault_chest_epic_open"
    ]
  },
  "vault_chest_omega_open": {
    "category": "master",
    "sounds": [
      "the_vault:chest/vault_chest_omega_open"
    ]
  },
  "vault_chest_rare_open": {
    "category": "master",
    "sounds": [
      "the_vault:chest/vault_chest_rare_open"
    ]
  },
  "favour_up": {
    "category": "player",
    "sounds": [
      "the_vault:favour_up"
    ]
  },
  "crate_open": {
    "category": "block",
    "sounds": [
      "the_vault:crate_open"
    ]
  },
  "artisan_smithing": {
    "category": "block",
    "sounds": [
      "the_vault:smithing/smithing1",
      "the_vault:smithing/smithing2",
      "the_vault:smithing/smithing3",
      "the_vault:smithing/smithing4"
    ]
  },
  "mob_trap": {
    "category": "block",
    "sounds": [
      "the_vault:mob_trap"
    ]
  },
  "disarm_trap": {
    "category": "block",
    "sounds": [
      "the_vault:disarm_trap"
    ]
  }
}